brizo/__init__.py
brizo/config.py
brizo/constants.py
brizo/exceptions.py
brizo/log.py
brizo/myapp.py
brizo/routes.py
brizo/run.py
brizo/util.py
ocean_brizo-0.9.7.dist-info/LICENSE
ocean_brizo-0.9.7.dist-info/METADATA
ocean_brizo-0.9.7.dist-info/WHEEL
ocean_brizo-0.9.7.dist-info/top_level.txt
ocean_brizo-0.9.7.dist-info/RECORD
