Metadata-Version: 2.1
Name: ocean-brizo
Version: 0.9.7
Summary: 🐳 Ocean Brizo.
Home-page: https://github.com/oceanprotocol/brizo
Author: leucothia
Author-email: devops@oceanprotocol.com
License: Apache Software License 2.0
Keywords: ocean-brizo
Platform: UNKNOWN
Classifier: Development Status :: 2 - Pre-Alpha
Classifier: Intended Audience :: Developers
Classifier: License :: OSI Approved :: Apache Software License
Classifier: Natural Language :: English
Classifier: Programming Language :: Python :: 3.6
Classifier: Programming Language :: Python :: 3.7
Requires-Dist: ocean-utils (==0.3.5)
Requires-Dist: ocean-keeper (==0.3.4)
Requires-Dist: ocean-secret-store-client (==0.0.2)
Requires-Dist: Flask (==1.0.2)
Requires-Dist: Flask-Cors (==3.0.6)
Requires-Dist: Flask-RESTful (==0.3.6)
Requires-Dist: flask-swagger (==0.2.13)
Requires-Dist: flask-swagger-ui (==3.6.0)
Requires-Dist: Jinja2 (>=2.10.1)
Requires-Dist: requests (>=2.21.0)
Requires-Dist: gunicorn (==19.9.0)
Requires-Dist: osmosis-azure-driver (==0.0.4)
Requires-Dist: osmosis-aws-driver (==0.0.4)
Requires-Dist: osmosis-driver-interface (==0.0.7)
Requires-Dist: osmosis-on-premise-driver (==0.0.6)
Requires-Dist: osmosis-ipfs-driver (==0.0.1)
Requires-Dist: Werkzeug (>=0.15.3)
Provides-Extra: dev
Requires-Dist: bumpversion ; extra == 'dev'
Requires-Dist: pkginfo ; extra == 'dev'
Requires-Dist: twine ; extra == 'dev'
Requires-Dist: watchdog ; extra == 'dev'
Requires-Dist: codacy-coverage ; extra == 'dev'
Requires-Dist: coverage ; extra == 'dev'
Requires-Dist: docker ; extra == 'dev'
Requires-Dist: mccabe ; extra == 'dev'
Requires-Dist: pylint ; extra == 'dev'
Requires-Dist: pytest ; extra == 'dev'
Requires-Dist: pytest-watch ; extra == 'dev'
Requires-Dist: tox ; extra == 'dev'
Requires-Dist: plecos ; extra == 'dev'
Provides-Extra: test
Requires-Dist: codacy-coverage ; extra == 'test'
Requires-Dist: coverage ; extra == 'test'
Requires-Dist: docker ; extra == 'test'
Requires-Dist: mccabe ; extra == 'test'
Requires-Dist: pylint ; extra == 'test'
Requires-Dist: pytest ; extra == 'test'
Requires-Dist: pytest-watch ; extra == 'test'
Requires-Dist: tox ; extra == 'test'
Requires-Dist: plecos ; extra == 'test'
